<?xml version="1.0" encoding="utf-8"?>
<document><pre><code>doc.title = 'Nano-Test-Site'

# Page (Home)
#&lt;tab/&gt;Wrapper
#&lt;tab/&gt;&lt;tab/&gt;Header 
#&lt;tab/&gt;&lt;tab/&gt;&lt;tab/&gt;Logo (+BurgerButton)
#&lt;tab/&gt;&lt;tab/&gt;&lt;tab/&gt;Navigation/TopMenu/MenuItem(s)
#  &lt;tab/&gt;&lt;tab/&gt;&lt;tab/&gt;Banner
#  &lt;tab/&gt;&lt;tab/&gt;&lt;tab/&gt;SlideShow (on Home)
#      &lt;tab/&gt;&lt;tab/&gt;Slides
#      &lt;tab/&gt;&lt;tab/&gt;SlideSide
#&lt;tab/&gt;&lt;tab/&gt;Content
#&lt;tab/&gt;&lt;tab/&gt;&lt;tab/&gt;Section(s)
#&lt;tab/&gt;&lt;tab/&gt;&lt;tab/&gt;&lt;tab/&gt;Introduction
#&lt;tab/&gt;&lt;tab/&gt;&lt;tab/&gt;&lt;tab/&gt;Main
#&lt;tab/&gt;&lt;tab/&gt;&lt;tab/&gt;&lt;tab/&gt;Side(s)
#&lt;tab/&gt;&lt;tab/&gt;Footer
#
# ----------------------------------------
# index.html
# ----------------------------------------
page.name = 'Home'
page.url = 'index.html'
content = page.select('Content')
box = content.newBanner()
</code></pre>

<h1>Headline on home page</h1>
<pre><code>section = content.newSection()
box = section.newIntroduction()
</code></pre>

<h2>This is an introduction head</h2>
<pre><code>box = section.newMain()
</code></pre>

<p>This is main text.<br />
This is main text.<br />
This is main text.<br />
This is main text.<br />
This is main text.<br />
This is main text.<br />
This is main text.<br />
This is main text.</p>
<pre><code>sides = section.newSides()
box = sides.newSide()
</code></pre>

<p>This is side text.<br />
This is side text.<br />
This is side text.<br />
This is side text.<br />
This is side text.<br />
This is side text.<br />
This is side text.<br />
This is side text.<br />
This is side text.</p>
<pre><code>box = sides.newSide()
</code></pre>

<p>This is a short side text.</p>
<pre><code>box = sides.newSide()
</code></pre>

<p>This is a second short side text.</p>
<pre><code>box = section.newMain()
</code></pre>

<p>This is main text.<br />
This is main text.<br />
This is main text.<br />
This is main text.<br />
This is main text.<br />
This is main text.<br />
This is main text.<br />
This is main text.</p>
<pre><code>sides = section.newSides()
box = sides.newSide()
</code></pre>

<p>This is a short side text.</p>
<pre><code>box = sides.newSide()
</code></pre>

<p>This is a second short side text.</p>
<pre><code>box = sides.newSide()
</code></pre>

<p>This is side text.<br />
This is side text.<br />
This is side text.<br />
This is side text.<br />
This is side text.<br />
This is side text.<br />
This is side text.<br />
This is side text.<br />
This is side text.</p>
<pre><code>box = section.newIntroduction()
</code></pre>

<h2>This is an introduction head</h2>
<pre><code>box = section.newMain()
</code></pre>

<p>This is main text.<br />
This is main text.<br />
This is main text.<br />
This is main text.<br />
This is main text.<br />
This is main text.<br />
This is main text.<br />
This is main text.</p>
<pre><code>sides = section.newSides()
box = sides.newSide()
</code></pre>

<p>This is side text.<br />
This is side text.<br />
This is side text.<br />
This is side text.<br />
This is side text.<br />
This is side text.<br />
This is side text.<br />
This is side text.<br />
This is side text.</p>
<pre><code>box = sides.newSide()
</code></pre>

<p>This is a short side text.</p>
<pre><code>box = sides.newSide()
</code></pre>

<p>This is a second short side text.</p></document>